tests/__init__.py
tests/test_image_generator.py
tests/test_parser.py
wrk2img/__init__.py
wrk2img/image_generator.py
wrk2img/main.py
wrk2img/parser.py
wrk2img-1.1.0.dist-info/LICENSE
wrk2img-1.1.0.dist-info/METADATA
wrk2img-1.1.0.dist-info/WHEEL
wrk2img-1.1.0.dist-info/entry_points.txt
wrk2img-1.1.0.dist-info/top_level.txt
wrk2img-1.1.0.dist-info/RECORD
