Metadata-Version: 2.1
Name: wrk2img
Version: 1.1.0
Summary: Create beautiful graph from wrk
Home-page: https://github.com/PPACI/wrk2img
Author: Pierre PACI
Author-email: 
License: MIT
Platform: UNKNOWN
Classifier: Operating System :: POSIX :: Linux
Classifier: Programming Language :: Python :: 3
Classifier: Topic :: System
Classifier: Topic :: System :: Networking
Requires-Python: >=3.5
Requires-Dist: matplotlib (>=2.0.0)
